Metadata-Version: 2.1
Name: domination
Version: 1.1
Summary: Real-time application in order to dominate Humans.
Home-page: UNKNOWN
Author: Baptiste Azéma
Author-email: baptiste@azema.tech
License: LICENSE
Platform: UNKNOWN
Requires-Python: ~=3.6
